{
  "discharge_mw": 490,
  "charge_mw": 763,
  "net_mw": -273,
  "timestamp": "2026-04-16 05:45:00-0500",
  "status": "live",
  "source": "ERCOT ESR Dashboard (live)",
  "fetched_utc": "2026-04-16T10:46:52.437930+00:00",
  "estimated_soc": 41,
  "history_soc": 40,
  "hourly_soc": {
    "0": 10,
    "1": 17,
    "2": 25,
    "3": 34,
    "4": 40,
    "5": 40,
    "6": 32,
    "7": 21,
    "8": 21,
    "9": 32,
    "10": 47,
    "11": 60,
    "12": 71,
    "13": 79,
    "14": 83,
    "15": 88,
    "16": 91,
    "17": 92,
    "18": 87,
    "19": 69,
    "20": 43,
    "21": 24,
    "22": 19,
    "23": 23
  },
  "hourly_avg_net": {
    "0": -786,
    "1": -1347,
    "2": -1539,
    "3": -1721,
    "4": -1131,
    "5": 22,
    "6": 1596,
    "7": 2002,
    "8": 19,
    "9": -1975,
    "10": -2849,
    "11": -2574,
    "12": -2117,
    "13": -1369,
    "14": -865,
    "15": -856,
    "16": -624,
    "17": -172,
    "18": 914,
    "19": 3520,
    "20": 4884,
    "21": 3452,
    "22": 972,
    "23": -632
  },
  "history_pts": 936,
  "history_days": 3.2,
  "current_hour_cdt": 5,
  "rate_adjustment": 1
}