{
  "discharge_mw": 26,
  "charge_mw": 2311,
  "net_mw": -2285,
  "timestamp": "2026-05-05 03:05:00-0500",
  "status": "live",
  "source": "ERCOT ESR Dashboard (live)",
  "fetched_utc": "2026-05-05T08:09:11.263954+00:00",
  "estimated_soc": 27,
  "history_soc": 25,
  "hourly_soc": {
    "0": 10,
    "1": 14,
    "2": 20,
    "3": 25,
    "4": 29,
    "5": 29,
    "6": 23,
    "7": 19,
    "8": 23,
    "9": 33,
    "10": 46,
    "11": 60,
    "12": 71,
    "13": 79,
    "14": 84,
    "15": 88,
    "16": 91,
    "17": 92,
    "18": 89,
    "19": 74,
    "20": 51,
    "21": 36,
    "22": 31,
    "23": 32
  },
  "hourly_avg_net": {
    "8": -908,
    "9": -2308,
    "10": -3003,
    "11": -3173,
    "12": -2669,
    "13": -1759,
    "14": -1298,
    "15": -829,
    "16": -632,
    "17": -278,
    "18": 605,
    "19": 3642,
    "20": 5217,
    "21": 3482,
    "22": 1078,
    "23": -260,
    "0": -532,
    "1": -1002,
    "2": -1210,
    "3": -1336,
    "4": -786,
    "5": -26,
    "6": 1339,
    "7": 990
  },
  "history_pts": 2832,
  "history_days": 9.8,
  "current_hour_cdt": 3,
  "rate_adjustment": 2
}